[
  {
    "YearMonth": 201301,
    "Soda_Volume": 718394219
  },
  {
    "YearMonth": 201302,
    "Soda_Volume": 753938444
  },
  {
    "YearMonth": 201303,
    "Soda_Volume": 892192092
  },
  {
    "YearMonth": 201304,
    "Soda_Volume": 838099501
  },
  {
    "YearMonth": 201305,
    "Soda_Volume": 864420003
  },
  {
    "YearMonth": 201306,
    "Soda_Volume": 889520921
  },
  {
    "YearMonth": 201307,
    "Soda_Volume": 869768947
  },
  {
    "YearMonth": 201308,
    "Soda_Volume": 757916529
  },
  {
    "YearMonth": 201309,
    "Soda_Volume": 789624076
  },
  {
    "YearMonth": 201310,
    "Soda_Volume": 791658684
  },
  {
    "YearMonth": 201311,
    "Soda_Volume": 806253783
  },
  {
    "YearMonth": 201312,
    "Soda_Volume": 785511080
  },
  {
    "YearMonth": 201401,
    "Soda_Volume": 763723622
  },
  {
    "YearMonth": 201402,
    "Soda_Volume": 734443953
  },
  {
    "YearMonth": 201403,
    "Soda_Volume": 828278650
  },
  {
    "YearMonth": 201404,
    "Soda_Volume": 873734739
  },
  {
    "YearMonth": 201405,
    "Soda_Volume": 887472626
  },
  {
    "YearMonth": 201406,
    "Soda_Volume": 865152191
  },
  {
    "YearMonth": 201407,
    "Soda_Volume": 837253085
  },
  {
    "YearMonth": 201408,
    "Soda_Volume": 867388593
  },
  {
    "YearMonth": 201409,
    "Soda_Volume": 767383003
  },
  {
    "YearMonth": 201410,
    "Soda_Volume": 790867324
  },
  {
    "YearMonth": 201411,
    "Soda_Volume": 715784335
  },
  {
    "YearMonth": 201412,
    "Soda_Volume": 696401477
  },
  {
    "YearMonth": 201501,
    "Soda_Volume": 762225057
  },
  {
    "YearMonth": 201502,
    "Soda_Volume": 717053984
  },
  {
    "YearMonth": 201503,
    "Soda_Volume": 871204688
  },
  {
    "YearMonth": 201504,
    "Soda_Volume": 860265890
  },
  {
    "YearMonth": 201505,
    "Soda_Volume": 927833877
  },
  {
    "YearMonth": 201506,
    "Soda_Volume": 899297932
  },
  {
    "YearMonth": 201507,
    "Soda_Volume": 897112934
  },
  {
    "YearMonth": 201508,
    "Soda_Volume": 875384686
  },
  {
    "YearMonth": 201509,
    "Soda_Volume": 742568762
  },
  {
    "YearMonth": 201510,
    "Soda_Volume": 761469815
  },
  {
    "YearMonth": 201511,
    "Soda_Volume": 798860058
  },
  {
    "YearMonth": 201512,
    "Soda_Volume": 822672453
  },
  {
    "YearMonth": 201601,
    "Soda_Volume": 787479774
  },
  {
    "YearMonth": 201602,
    "Soda_Volume": 729418593
  },
  {
    "YearMonth": 201603,
    "Soda_Volume": 852685632
  },
  {
    "YearMonth": 201604,
    "Soda_Volume": 864686985
  },
  {
    "YearMonth": 201605,
    "Soda_Volume": 953568835
  },
  {
    "YearMonth": 201606,
    "Soda_Volume": 912787084
  },
  {
    "YearMonth": 201607,
    "Soda_Volume": 938467950
  },
  {
    "YearMonth": 201608,
    "Soda_Volume": 930171702
  },
  {
    "YearMonth": 201609,
    "Soda_Volume": 904326556
  },
  {
    "YearMonth": 201610,
    "Soda_Volume": 889355958
  },
  {
    "YearMonth": 201611,
    "Soda_Volume": 883100473
  },
  {
    "YearMonth": 201612,
    "Soda_Volume": 890156001
  },
  {
    "YearMonth": 201701,
    "Soda_Volume": 845614054
  },
  {
    "YearMonth": 201702,
    "Soda_Volume": 850913048
  },
  {
    "YearMonth": 201703,
    "Soda_Volume": 886129111
  },
  {
    "YearMonth": 201704,
    "Soda_Volume": 940912941
  },
  {
    "YearMonth": 201705,
    "Soda_Volume": 917412482
  },
  {
    "YearMonth": 201706,
    "Soda_Volume": 928366256
  },
  {
    "YearMonth": 201707,
    "Soda_Volume": 926635433
  },
  {
    "YearMonth": 201708,
    "Soda_Volume": 1049868815
  },
  {
    "YearMonth": 201709,
    "Soda_Volume": 984438234
  },
  {
    "YearMonth": 201710,
    "Soda_Volume": 996763883
  },
  {
    "YearMonth": 201711,
    "Soda_Volume": 967899589
  },
  {
    "YearMonth": 201712,
    "Soda_Volume": 919709619
  }
]